Workbook

Sheet JobsPikr Raw Data
A1: Job ID | B1: Company | C1: Job Title | D1: Job Category | E1: Location | F1: Date Posted | G1: Skills | H1: Level | I1: Remote | J1: Job Description
A2: JP-001 | B2: BharatPe | C2: QA Engineer – Mobile App | D2: Operations & Support | E2: Pune | F2: 46050 | G2: Manual Testing, Bug Tracking, Postman, SQL | H2: Entry | I2: Yes | J2: Conducting quality assurance for mobile app and API integrations
A3: JP-002 | B3: Navi | C3: Manager – Analytics & Insights | D3: Data Science | E3: Mumbai | F3: 46050 | G3: Python, SQL, Team Leadership, Stakeholder Mgmt | H3: Mid | I3: No | J3: Extracting insights from transaction data to inform product expansion strategy
A4: JP-003 | B4: Jupiter | C4: NLP Engineer – Chatbot & Support | D4: Engineering (AI/ML) | E4: Pune | F4: 46049 | G4: Transformers, BERT, spaCy, Python | H4: Mid | I4: Yes | J4: Creating NLP-driven chatbot solutions to enhance customer support and reduce operational costs
A5: JP-004 | B5: EarlySalary | C5: Associate PM – Onboarding | D5: Product Management | E5: Delhi NCR | F5: 46048 | G5: Wireframing, Agile, User Research, Communication | H5: Entry | I5: No | J5: Contributing to team initiatives and operational excellence
A6: JP-005 | B6: Cred | C6: Product Lead – Payments | D6: Product Management | E6: Hyderabad | F6: 46048 | G6: Roadmap, Stakeholder Mgmt, Agile, Fintech API | H6: Mid | I6: Yes | J6: Leading platform infrastructure development to support multi-product scaling
A7: JP-006 | B7: FamPay | C7: Accountant | D7: Operations & Support | E7: Pune | F7: 46048 | G7: Tally, Excel, Financial Reporting, Taxation | H7: Mid | I7: Yes | J7: Driving sales initiatives for existing product lines and customer segments
A8: JP-007 | B8: Razorpay | C8: Product Manager – Credit Stack | D8: Product Management | E8: Mumbai | F8: 46048 | G8: SQL, APIs, System Design, Product Strategy | H8: Mid | I8: Yes | J8: Defining product roadmap for embedded finance features and API integrations
A9: JP-008 | B9: Razorpay | C9: Director – Platform Engineering | D9: Engineering Leadership | E9: Mumbai | F9: 46047 | G9: Infrastructure, AWS, Cloud Architecture, Scalability | H9: Senior | I9: No | J9: Scaling platform architecture to support 10x growth in transaction volume
A10: JP-009 | B10: EarlySalary | C10: Growth Manager – User Acquisition | D10: Sales/GTM | E10: Bangalore | F10: 46047 | G10: Digital Marketing, Performance Marketing, SQL | H10: Mid | I10: No | J10: Contributing to team initiatives and operational excellence
A11: JP-010 | B11: Navi | C11: Senior ML Engineer – Fraud | D11: Engineering (AI/ML) | E11: Hyderabad | F11: 46047 | G11: Java, Python, Scikit-learn, SQL | H11: Mid | I11: No | J11: Developing machine learning systems for real-time fraud detection and risk assessment
A12: JP-011 | B12: ZestMoney | C12: QA Analyst – Payments API | D12: Operations & Support | E12: Delhi NCR | F12: 46046 | G12: Manual Testing, Bug Tracking, Postman, SQL | H12: Entry | I12: No | J12: Ensuring quality and reliability of payment processing systems through testing
A13: JP-012 | B13: Lendingkart | C13: Data Science Manager – Analytics | D13: Data Science | E13: Bangalore | F13: 46045 | G13: Python, SQL, Team Leadership, Stakeholder Mgmt | H13: Mid | I13: No | J13: Building dashboards and providing data insights for operational teams
... A131: JP-130 | B131: PhonePe | C131: Data Science Manager – Analytics | D131: Data Science | E131: Pune | F131: 45992 | G131: Python, SQL, Team Leadership, Stakeholder Mgmt | H131: Mid | I131: Yes | J131: Analyzing transaction data and generating reports for business stakeholders

Sheet Hiring Velocity
A1: Company | B1: Dec(2025) Jobs | C1: Jan(2026) Jobs | D1: Spike Ratio | E1: Momentum Flag
A2: {=_xlfn._xlws.SORT(_xlfn.UNIQUE('JobsPikr Raw Data'!B2:B131))} -> BharatPe | B2: =COUNTIFS('JobsPikr Raw Data'!$B:$B,$A2,'JobsPikr Raw Data'!$F:$F,">="&DATE(2025,12,1),'JobsPikr Raw Data'!$F:$F,"<"&DATE(2026,1,1)) -> 3 | C2: =COUNTIFS('JobsPikr Raw Data'!$B:$B,$A2,'JobsPikr Raw Data'!$F:$F,">="&DATE(2026,1,1),'JobsPikr Raw Data'!$F:$F,"<"&DATE(2026,2,1)) -> 2 | D2: =IF(B2=0,"-",C2/B2) -> 0.66666667 | E2: =IF(D2>=2,"High Momentum",IF(D2>=1.2,"Moderate Growth","Stable/Declining")) -> Stable/Declining
A3: Cred | B3: =COUNTIFS('JobsPikr Raw Data'!$B:$B,$A3,'JobsPikr Raw Data'!$F:$F,">="&DATE(2025,12,1),'JobsPikr Raw Data'!$F:$F,"<"&DATE(2026,1,1)) -> 3 | C3: =COUNTIFS('JobsPikr Raw Data'!$B:$B,$A3,'JobsPikr Raw Data'!$F:$F,">="&DATE(2026,1,1),'JobsPikr Raw Data'!$F:$F,"<"&DATE(2026,2,1)) -> 8 | D3: =IF(B3=0,"-",C3/B3) -> 2.6666667 | E3: =IF(D3>=2,"High Momentum",IF(D3>=1.2,"Moderate Growth","Stable/Declining")) -> High Momentum
A4: EarlySalary | B4: =COUNTIFS('JobsPikr Raw Data'!$B:$B,$A4,'JobsPikr Raw Data'!$F:$F,">="&DATE(2025,12,1),'JobsPikr Raw Data'!$F:$F,"<"&DATE(2026,1,1)) -> 2 | C4: =COUNTIFS('JobsPikr Raw Data'!$B:$B,$A4,'JobsPikr Raw Data'!$F:$F,">="&DATE(2026,1,1),'JobsPikr Raw Data'!$F:$F,"<"&DATE(2026,2,1)) -> 3 | D4: =IF(B4=0,"-",C4/B4) -> 1.5 | E4: =IF(D4>=2,"High Momentum",IF(D4>=1.2,"Moderate Growth","Stable/Declining")) -> Moderate Growth
A5: FamPay | B5: =COUNTIFS('JobsPikr Raw Data'!$B:$B,$A5,'JobsPikr Raw Data'!$F:$F,">="&DATE(2025,12,1),'JobsPikr Raw Data'!$F:$F,"<"&DATE(2026,1,1)) -> 3 | C5: =COUNTIFS('JobsPikr Raw Data'!$B:$B,$A5,'JobsPikr Raw Data'!$F:$F,">="&DATE(2026,1,1),'JobsPikr Raw Data'!$F:$F,"<"&DATE(2026,2,1)) -> 2 | D5: =IF(B5=0,"-",C5/B5) -> 0.66666667 | E5: =IF(D5>=2,"High Momentum",IF(D5>=1.2,"Moderate Growth","Stable/Declining")) -> Stable/Declining
A6: FlexiLoans | B6: =COUNTIFS('JobsPikr Raw Data'!$B:$B,$A6,'JobsPikr Raw Data'!$F:$F,">="&DATE(2025,12,1),'JobsPikr Raw Data'!$F:$F,"<"&DATE(2026,1,1)) -> 3 | C6: =COUNTIFS('JobsPikr Raw Data'!$B:$B,$A6,'JobsPikr Raw Data'!$F:$F,">="&DATE(2026,1,1),'JobsPikr Raw Data'!$F:$F,"<"&DATE(2026,2,1)) -> 3 | D6: =IF(B6=0,"-",C6/B6) -> 1 | E6: =IF(D6>=2,"High Momentum",IF(D6>=1.2,"Moderate Growth","Stable/Declining")) -> Stable/Declining
A7: Jupiter | B7: =COUNTIFS('JobsPikr Raw Data'!$B:$B,$A7,'JobsPikr Raw Data'!$F:$F,">="&DATE(2025,12,1),'JobsPikr Raw Data'!$F:$F,"<"&DATE(2026,1,1)) -> 2 | C7: =COUNTIFS('JobsPikr Raw Data'!$B:$B,$A7,'JobsPikr Raw Data'!$F:$F,">="&DATE(2026,1,1),'JobsPikr Raw Data'!$F:$F,"<"&DATE(2026,2,1)) -> 6 | D7: =IF(B7=0,"-",C7/B7) -> 3 | E7: =IF(D7>=2,"High Momentum",IF(D7>=1.2,"Moderate Growth","Stable/Declining")) -> High Momentum
A8: KreditBee | B8: =COUNTIFS('JobsPikr Raw Data'!$B:$B,$A8,'JobsPikr Raw Data'!$F:$F,">="&DATE(2025,12,1),'JobsPikr Raw Data'!$F:$F,"<"&DATE(2026,1,1)) -> 2 | C8: =COUNTIFS('JobsPikr Raw Data'!$B:$B,$A8,'JobsPikr Raw Data'!$F:$F,">="&DATE(2026,1,1),'JobsPikr Raw Data'!$F:$F,"<"&DATE(2026,2,1)) -> 3 | D8: =IF(B8=0,"-",C8/B8) -> 1.5 | E8: =IF(D8>=2,"High Momentum",IF(D8>=1.2,"Moderate Growth","Stable/Declining")) -> Moderate Growth
A9: Lendingkart | B9: =COUNTIFS('JobsPikr Raw Data'!$B:$B,$A9,'JobsPikr Raw Data'!$F:$F,">="&DATE(2025,12,1),'JobsPikr Raw Data'!$F:$F,"<"&DATE(2026,1,1)) -> 2 | C9: =COUNTIFS('JobsPikr Raw Data'!$B:$B,$A9,'JobsPikr Raw Data'!$F:$F,">="&DATE(2026,1,1),'JobsPikr Raw Data'!$F:$F,"<"&DATE(2026,2,1)) -> 3 | D9: =IF(B9=0,"-",C9/B9) -> 1.5 | E9: =IF(D9>=2,"High Momentum",IF(D9>=1.2,"Moderate Growth","Stable/Declining")) -> Moderate Growth
A10: MobiKwik | B10: =COUNTIFS('JobsPikr Raw Data'!$B:$B,$A10,'JobsPikr Raw Data'!$F:$F,">="&DATE(2025,12,1),'JobsPikr Raw Data'!$F:$F,"<"&DATE(2026,1,1)) -> 3 | C10: =COUNTIFS('JobsPikr Raw Data'!$B:$B,$A10,'JobsPikr Raw Data'!$F:$F,">="&DATE(2026,1,1),'JobsPikr Raw Data'!$F:$F,"<"&DATE(2026,2,1)) -> 2 | D10: =IF(B10=0,"-",C10/B10) -> 0.66666667 | E10: =IF(D10>=2,"High Momentum",IF(D10>=1.2,"Moderate Growth","Stable/Declining")) -> Stable/Declining
A11: MoneyTap | B11: =COUNTIFS('JobsPikr Raw Data'!$B:$B,$A11,'JobsPikr Raw Data'!$F:$F,">="&DATE(2025,12,1),'JobsPikr Raw Data'!$F:$F,"<"&DATE(2026,1,1)) -> 2 | C11: =COUNTIFS('JobsPikr Raw Data'!$B:$B,$A11,'JobsPikr Raw Data'!$F:$F,">="&DATE(2026,1,1),'JobsPikr Raw Data'!$F:$F,"<"&DATE(2026,2,1)) -> 3 | D11: =IF(B11=0,"-",C11/B11) -> 1.5 | E11: =IF(D11>=2,"High Momentum",IF(D11>=1.2,"Moderate Growth","Stable/Declining")) -> Moderate Growth
A12: Navi | B12: =COUNTIFS('JobsPikr Raw Data'!$B:$B,$A12,'JobsPikr Raw Data'!$F:$F,">="&DATE(2025,12,1),'JobsPikr Raw Data'!$F:$F,"<"&DATE(2026,1,1)) -> 4 | C12: =COUNTIFS('JobsPikr Raw Data'!$B:$B,$A12,'JobsPikr Raw Data'!$F:$F,">="&DATE(2026,1,1),'JobsPikr Raw Data'!$F:$F,"<"&DATE(2026,2,1)) -> 8 | D12: =IF(B12=0,"-",C12/B12) -> 2 | E12: =IF(D12>=2,"High Momentum",IF(D12>=1.2,"Moderate Growth","Stable/Declining")) -> High Momentum
A13: Open | B13: =COUNTIFS('JobsPikr Raw Data'!$B:$B,$A13,'JobsPikr Raw Data'!$F:$F,">="&DATE(2025,12,1),'JobsPikr Raw Data'!$F:$F,"<"&DATE(2026,1,1)) -> 2 | C13: =COUNTIFS('JobsPikr Raw Data'!$B:$B,$A13,'JobsPikr Raw Data'!$F:$F,">="&DATE(2026,1,1),'JobsPikr Raw Data'!$F:$F,"<"&DATE(2026,2,1)) -> 3 | D13: =IF(B13=0,"-",C13/B13) -> 1.5 | E13: =IF(D13>=2,"High Momentum",IF(D13>=1.2,"Moderate Growth","Stable/Declining")) -> Moderate Growth
A14: Paytm | B14: =COUNTIFS('JobsPikr Raw Data'!$B:$B,$A14,'JobsPikr Raw Data'!$F:$F,">="&DATE(2025,12,1),'JobsPikr Raw Data'!$F:$F,"<"&DATE(2026,1,1)) -> 3 | C14: =COUNTIFS('JobsPikr Raw Data'!$B:$B,$A14,'JobsPikr Raw Data'!$F:$F,">="&DATE(2026,1,1),'JobsPikr Raw Data'!$F:$F,"<"&DATE(2026,2,1)) -> 3 | D14: =IF(B14=0,"-",C14/B14) -> 1 | E14: =IF(D14>=2,"High Momentum",IF(D14>=1.2,"Moderate Growth","Stable/Declining")) -> Stable/Declining
... A21: ZestMoney | B21: =COUNTIFS('JobsPikr Raw Data'!$B:$B,$A21,'JobsPikr Raw Data'!$F:$F,">="&DATE(2025,12,1),'JobsPikr Raw Data'!$F:$F,"<"&DATE(2026,1,1)) -> 3 | C21: =COUNTIFS('JobsPikr Raw Data'!$B:$B,$A21,'JobsPikr Raw Data'!$F:$F,">="&DATE(2026,1,1),'JobsPikr Raw Data'!$F:$F,"<"&DATE(2026,2,1)) -> 3 | D21: =IF(B21=0,"-",C21/B21) -> 1 | E21: =IF(D21>=2,"High Momentum",IF(D21>=1.2,"Moderate Growth","Stable/Declining")) -> Stable/Declining

Sheet Strategic Focus
A1: Company | B1: Total Jobs | C1: Weighted Role Score | D1: Strategic Focus (0–100) | E1: Velocity Score | F1: HMS Score (0–100)
A2: {=_xlfn._xlws.SORT(_xlfn.UNIQUE('JobsPikr Raw Data'!B2:B131))} -> BharatPe | B2: =COUNTIF('JobsPikr Raw Data'!B:B, A2) -> 5 | C2: {=AVERAGE(IF('JobsPikr Raw Data'!$B$2:$B$131=$A2,_xlfn.XLOOKUP('JobsPikr Raw Data'!$D$2:$D$131,$K$5:$K$11,$L$5:$L$11,40),""))} -> 62 | D2: =ROUND(C2,0) -> 62 | E2: =_xlfn.XLOOKUP(_xlfn.XLOOKUP(A2,'Hiring Velocity'!$A$2:$A$21,'Hiring Velocity'!$E$2:$E$21),$J$20:$J$22,$K$20:$K$22,0) -> 30 | F2: =ROUND(0.5*E2 + 0.5*D2,0) -> 46
A3: Cred | B3: =COUNTIF('JobsPikr Raw Data'!B:B, A3) -> 11 | C3: {=AVERAGE(IF('JobsPikr Raw Data'!$B$2:$B$131=$A3,_xlfn.XLOOKUP('JobsPikr Raw Data'!$D$2:$D$131,$K$5:$K$11,$L$5:$L$11,40),""))} -> 85 | D3: =ROUND(C3,0) -> 85 | E3: =_xlfn.XLOOKUP(_xlfn.XLOOKUP(A3,'Hiring Velocity'!$A$2:$A$21,'Hiring Velocity'!$E$2:$E$21),$J$20:$J$22,$K$20:$K$22,0) -> 100 | F3: =ROUND(0.5*E3 + 0.5*D3,0) -> 93 | L3: Role Category Weight Mapping (Strategic Focus Model)
A4: EarlySalary | B4: =COUNTIF('JobsPikr Raw Data'!B:B, A4) -> 5 | C4: {=AVERAGE(IF('JobsPikr Raw Data'!$B$2:$B$131=$A4,_xlfn.XLOOKUP('JobsPikr Raw Data'!$D$2:$D$131,$K$5:$K$11,$L$5:$L$11,40),""))} -> 77 | D4: =ROUND(C4,0) -> 77 | E4: =_xlfn.XLOOKUP(_xlfn.XLOOKUP(A4,'Hiring Velocity'!$A$2:$A$21,'Hiring Velocity'!$E$2:$E$21),$J$20:$J$22,$K$20:$K$22,0) -> 70 | F4: =ROUND(0.5*E4 + 0.5*D4,0) -> 74 | K4: Category | L4: Weight | M4: Reason
A5: FamPay | B5: =COUNTIF('JobsPikr Raw Data'!B:B, A5) -> 5 | C5: {=AVERAGE(IF('JobsPikr Raw Data'!$B$2:$B$131=$A5,_xlfn.XLOOKUP('JobsPikr Raw Data'!$D$2:$D$131,$K$5:$K$11,$L$5:$L$11,40),""))} -> 48 | D5: =ROUND(C5,0) -> 48 | E5: =_xlfn.XLOOKUP(_xlfn.XLOOKUP(A5,'Hiring Velocity'!$A$2:$A$21,'Hiring Velocity'!$E$2:$E$21),$J$20:$J$22,$K$20:$K$22,0) -> 30 | F5: =ROUND(0.5*E5 + 0.5*D5,0) -> 39 | K5: Engineering (AI/ML) | L5: 95 | M5: Strong signal of product + automation investment
A6: FlexiLoans | B6: =COUNTIF('JobsPikr Raw Data'!B:B, A6) -> 6 | C6: {=AVERAGE(IF('JobsPikr Raw Data'!$B$2:$B$131=$A6,_xlfn.XLOOKUP('JobsPikr Raw Data'!$D$2:$D$131,$K$5:$K$11,$L$5:$L$11,40),""))} -> 63.333333 | D6: =ROUND(C6,0) -> 63 | E6: =_xlfn.XLOOKUP(_xlfn.XLOOKUP(A6,'Hiring Velocity'!$A$2:$A$21,'Hiring Velocity'!$E$2:$E$21),$J$20:$J$22,$K$20:$K$22,0) -> 30 | F6: =ROUND(0.5*E6 + 0.5*D6,0) -> 47 | K6: Data Science | L6: 90 | M6: Risk models + personalization scaling
A7: Jupiter | B7: =COUNTIF('JobsPikr Raw Data'!B:B, A7) -> 8 | C7: {=AVERAGE(IF('JobsPikr Raw Data'!$B$2:$B$131=$A7,_xlfn.XLOOKUP('JobsPikr Raw Data'!$D$2:$D$131,$K$5:$K$11,$L$5:$L$11,40),""))} -> 85 | D7: =ROUND(C7,0) -> 85 | E7: =_xlfn.XLOOKUP(_xlfn.XLOOKUP(A7,'Hiring Velocity'!$A$2:$A$21,'Hiring Velocity'!$E$2:$E$21),$J$20:$J$22,$K$20:$K$22,0) -> 100 | F7: =ROUND(0.5*E7 + 0.5*D7,0) -> 93 | K7: Product Management | L7: 85 | M7: Platform expansion and roadmap acceleration
A8: KreditBee | B8: =COUNTIF('JobsPikr Raw Data'!B:B, A8) -> 5 | C8: {=AVERAGE(IF('JobsPikr Raw Data'!$B$2:$B$131=$A8,_xlfn.XLOOKUP('JobsPikr Raw Data'!$D$2:$D$131,$K$5:$K$11,$L$5:$L$11,40),""))} -> 73 | D8: =ROUND(C8,0) -> 73 | E8: =_xlfn.XLOOKUP(_xlfn.XLOOKUP(A8,'Hiring Velocity'!$A$2:$A$21,'Hiring Velocity'!$E$2:$E$21),$J$20:$J$22,$K$20:$K$22,0) -> 70 | F8: =ROUND(0.5*E8 + 0.5*D8,0) -> 72 | K8: Engineering Leadership | L8: 80 | M8: Scaling signal
A9: Lendingkart | B9: =COUNTIF('JobsPikr Raw Data'!B:B, A9) -> 5 | C9: {=AVERAGE(IF('JobsPikr Raw Data'!$B$2:$B$131=$A9,_xlfn.XLOOKUP('JobsPikr Raw Data'!$D$2:$D$131,$K$5:$K$11,$L$5:$L$11,40),""))} -> 72 | D9: =ROUND(C9,0) -> 72 | E9: =_xlfn.XLOOKUP(_xlfn.XLOOKUP(A9,'Hiring Velocity'!$A$2:$A$21,'Hiring Velocity'!$E$2:$E$21),$J$20:$J$22,$K$20:$K$22,0) -> 70 | F9: =ROUND(0.5*E9 + 0.5*D9,0) -> 71 | K9: Risk & Compliance | L9: 75 | M9: Regulatory scaling in fintech
A10: MobiKwik | B10: =COUNTIF('JobsPikr Raw Data'!B:B, A10) -> 5 | C10: {=AVERAGE(IF('JobsPikr Raw Data'!$B$2:$B$131=$A10,_xlfn.XLOOKUP('JobsPikr Raw Data'!$D$2:$D$131,$K$5:$K$11,$L$5:$L$11,40),""))} -> 53 | D10: =ROUND(C10,0) -> 53 | E10: =_xlfn.XLOOKUP(_xlfn.XLOOKUP(A10,'Hiring Velocity'!$A$2:$A$21,'Hiring Velocity'!$E$2:$E$21),$J$20:$J$22,$K$20:$K$22,0) -> 30 | F10: =ROUND(0.5*E10 + 0.5*D10,0) -> 42 | K10: Sales/GTM | L10: 60 | M10: Monetization and distribution push
A11: MoneyTap | B11: =COUNTIF('JobsPikr Raw Data'!B:B, A11) -> 5 | C11: {=AVERAGE(IF('JobsPikr Raw Data'!$B$2:$B$131=$A11,_xlfn.XLOOKUP('JobsPikr Raw Data'!$D$2:$D$131,$K$5:$K$11,$L$5:$L$11,40),""))} -> 73 | D11: =ROUND(C11,0) -> 73 | E11: =_xlfn.XLOOKUP(_xlfn.XLOOKUP(A11,'Hiring Velocity'!$A$2:$A$21,'Hiring Velocity'!$E$2:$E$21),$J$20:$J$22,$K$20:$K$22,0) -> 70 | F11: =ROUND(0.5*E11 + 0.5*D11,0) -> 72 | K11: Operations & Support | L11: 40 | M11: Maintenance hiring, not growth signal
A12: Navi | B12: =COUNTIF('JobsPikr Raw Data'!B:B, A12) -> 12 | C12: {=AVERAGE(IF('JobsPikr Raw Data'!$B$2:$B$131=$A12,_xlfn.XLOOKUP('JobsPikr Raw Data'!$D$2:$D$131,$K$5:$K$11,$L$5:$L$11,40),""))} -> 82.5 | D12: =ROUND(C12,0) -> 83 | E12: =_xlfn.XLOOKUP(_xlfn.XLOOKUP(A12,'Hiring Velocity'!$A$2:$A$21,'Hiring Velocity'!$E$2:$E$21),$J$20:$J$22,$K$20:$K$22,0) -> 100 | F12: =ROUND(0.5*E12 + 0.5*D12,0) -> 92
A13: Open | B13: =COUNTIF('JobsPikr Raw Data'!B:B, A13) -> 5 | C13: {=AVERAGE(IF('JobsPikr Raw Data'!$B$2:$B$131=$A13,_xlfn.XLOOKUP('JobsPikr Raw Data'!$D$2:$D$131,$K$5:$K$11,$L$5:$L$11,40),""))} -> 77 | D13: =ROUND(C13,0) -> 77 | E13: =_xlfn.XLOOKUP(_xlfn.XLOOKUP(A13,'Hiring Velocity'!$A$2:$A$21,'Hiring Velocity'!$E$2:$E$21),$J$20:$J$22,$K$20:$K$22,0) -> 70 | F13: =ROUND(0.5*E13 + 0.5*D13,0) -> 74
A14: Paytm | B14: =COUNTIF('JobsPikr Raw Data'!B:B, A14) -> 6 | C14: {=AVERAGE(IF('JobsPikr Raw Data'!$B$2:$B$131=$A14,_xlfn.XLOOKUP('JobsPikr Raw Data'!$D$2:$D$131,$K$5:$K$11,$L$5:$L$11,40),""))} -> 65 | D14: =ROUND(C14,0) -> 65 | E14: =_xlfn.XLOOKUP(_xlfn.XLOOKUP(A14,'Hiring Velocity'!$A$2:$A$21,'Hiring Velocity'!$E$2:$E$21),$J$20:$J$22,$K$20:$K$22,0) -> 30 | F14: =ROUND(0.5*E14 + 0.5*D14,0) -> 48
A15: PhonePe | B15: =COUNTIF('JobsPikr Raw Data'!B:B, A15) -> 5 | C15: {=AVERAGE(IF('JobsPikr Raw Data'!$B$2:$B$131=$A15,_xlfn.XLOOKUP('JobsPikr Raw Data'!$D$2:$D$131,$K$5:$K$11,$L$5:$L$11,40),""))} -> 80 | D15: =ROUND(C15,0) -> 80 | E15: =_xlfn.XLOOKUP(_xlfn.XLOOKUP(A15,'Hiring Velocity'!$A$2:$A$21,'Hiring Velocity'!$E$2:$E$21),$J$20:$J$22,$K$20:$K$22,0) -> 70 | F15: =ROUND(0.5*E15 + 0.5*D15,0) -> 75
A16: Pine Labs | B16: =COUNTIF('JobsPikr Raw Data'!B:B, A16) -> 8 | C16: {=AVERAGE(IF('JobsPikr Raw Data'!$B$2:$B$131=$A16,_xlfn.XLOOKUP('JobsPikr Raw Data'!$D$2:$D$131,$K$5:$K$11,$L$5:$L$11,40),""))} -> 83.125 | D16: =ROUND(C16,0) -> 83 | E16: =_xlfn.XLOOKUP(_xlfn.XLOOKUP(A16,'Hiring Velocity'!$A$2:$A$21,'Hiring Velocity'!$E$2:$E$21),$J$20:$J$22,$K$20:$K$22,0) -> 100 | F16: =ROUND(0.5*E16 + 0.5*D16,0) -> 92
A17: Razorpay | B17: =COUNTIF('JobsPikr Raw Data'!B:B, A17) -> 13 | C17: {=AVERAGE(IF('JobsPikr Raw Data'!$B$2:$B$131=$A17,_xlfn.XLOOKUP('JobsPikr Raw Data'!$D$2:$D$131,$K$5:$K$11,$L$5:$L$11,40),""))} -> 85 | D17: =ROUND(C17,0) -> 85 | E17: =_xlfn.XLOOKUP(_xlfn.XLOOKUP(A17,'Hiring Velocity'!$A$2:$A$21,'Hiring Velocity'!$E$2:$E$21),$J$20:$J$22,$K$20:$K$22,0) -> 100 | F17: =ROUND(0.5*E17 + 0.5*D17,0) -> 93
A18: Simpl | B18: =COUNTIF('JobsPikr Raw Data'!B:B, A18) -> 5 | C18: {=AVERAGE(IF('JobsPikr Raw Data'!$B$2:$B$131=$A18,_xlfn.XLOOKUP('JobsPikr Raw Data'!$D$2:$D$131,$K$5:$K$11,$L$5:$L$11,40),""))} -> 62 | D18: =ROUND(C18,0) -> 62 | E18: =_xlfn.XLOOKUP(_xlfn.XLOOKUP(A18,'Hiring Velocity'!$A$2:$A$21,'Hiring Velocity'!$E$2:$E$21),$J$20:$J$22,$K$20:$K$22,0) -> 30 | F18: =ROUND(0.5*E18 + 0.5*D18,0) -> 46 | J18: Velocity Score Mapping
A19: Slice | B19: =COUNTIF('JobsPikr Raw Data'!B:B, A19) -> 5 | C19: {=AVERAGE(IF('JobsPikr Raw Data'!$B$2:$B$131=$A19,_xlfn.XLOOKUP('JobsPikr Raw Data'!$D$2:$D$131,$K$5:$K$11,$L$5:$L$11,40),""))} -> 66 | D19: =ROUND(C19,0) -> 66 | E19: =_xlfn.XLOOKUP(_xlfn.XLOOKUP(A19,'Hiring Velocity'!$A$2:$A$21,'Hiring Velocity'!$E$2:$E$21),$J$20:$J$22,$K$20:$K$22,0) -> 70 | F19: =ROUND(0.5*E19 + 0.5*D19,0) -> 68 | J19: Momentum Flag | K19: Velocity Score
A20: Uni Cards | B20: =COUNTIF('JobsPikr Raw Data'!B:B, A20) -> 5 | C20: {=AVERAGE(IF('JobsPikr Raw Data'!$B$2:$B$131=$A20,_xlfn.XLOOKUP('JobsPikr Raw Data'!$D$2:$D$131,$K$5:$K$11,$L$5:$L$11,40),""))} -> 66 | D20: =ROUND(C20,0) -> 66 | E20: =_xlfn.XLOOKUP(_xlfn.XLOOKUP(A20,'Hiring Velocity'!$A$2:$A$21,'Hiring Velocity'!$E$2:$E$21),$J$20:$J$22,$K$20:$K$22,0) -> 70 | F20: =ROUND(0.5*E20 + 0.5*D20,0) -> 68 | J20: High Momentum | K20: 100
A21: ZestMoney | B21: =COUNTIF('JobsPikr Raw Data'!B:B, A21) -> 6 | C21: {=AVERAGE(IF('JobsPikr Raw Data'!$B$2:$B$131=$A21,_xlfn.XLOOKUP('JobsPikr Raw Data'!$D$2:$D$131,$K$5:$K$11,$L$5:$L$11,40),""))} -> 63.333333 | D21: =ROUND(C21,0) -> 63 | E21: =_xlfn.XLOOKUP(_xlfn.XLOOKUP(A21,'Hiring Velocity'!$A$2:$A$21,'Hiring Velocity'!$E$2:$E$21),$J$20:$J$22,$K$20:$K$22,0) -> 30 | F21: =ROUND(0.5*E21 + 0.5*D21,0) -> 47 | J21: Moderate Growth | K21: 70
J22: Stable/Declining | K22: 30
J26: Hiring Momentum Score (HMS) Formula
J27: HMS=0.5×Velocity+0.5×StrategicFocus
